[
  {
    "id": "1681543794000",
    "title": "Web3技术发展趋势",
    "content": "Web3技术作为互联网的新范式正迅速发展。从比特币区块链到以太坊智能合约，再到Layer2解决方案，Web3生态系统日益完善。Layer2技术显著提高了交易吞吐量，DID协议帮助用户掌控自己的数据主权。",
    "createdAt": "2023-04-15T08:23:14.000Z",
    "updatedAt": "2023-04-15T08:23:14.000Z",
    "comments": []
  },
  {
    "id": "1681543894000",
    "title": "终身学习的重要性",
    "content": "在知识爆炸的时代，终身学习从选择变成了必需。对技术从业者而言，保持知识更新是关键。建立学习系统需要精选信息源、组织知识并通过实践输出。关注基础原理，保持开放与好奇，才能在变革中立于不败之地。",
    "createdAt": "2023-04-15T08:24:54.000Z",
    "updatedAt": "2023-04-15T08:24:54.000Z",
    "comments": []
  },
  {
    "id": "1744714995958",
    "title": "2025-4-15 Hellow World",
    "content": "test",
    "createdAt": "2025-04-15T11:03:15.958Z",
    "updatedAt": "2025-04-15T11:03:15.958Z",
    "comments": [
      {
        "id": "1744718062893",
        "content": "hellow",
        "author": "0x3A7c7DfA73d9D697655eBEe200B471e4E4C2B471",
        "createdAt": "2025-04-15T11:54:22.893Z"
      },
      {
        "id": "1744718098121",
        "content": "Hi",
        "author": "0x01598CdD08c9737a84ead88BAaED1ed4c3330cD2",
        "createdAt": "2025-04-15T11:54:58.121Z"
      },
      {
        "id": "1744718141489",
        "content": "delete me",
        "author": "0x01598CdD08c9737a84ead88BAaED1ed4c3330cD2",
        "createdAt": "2025-04-15T11:55:41.489Z"
      }
    ]
  },
  {
    "id": "1744763927978",
    "title": "2025-4-16 known issue for this website",
    "content": "1. The formation welcome sentence for this website may be wrong , causing some items being shaded while the welcome sentecce showed\n\n2. The description of hobbit can be improved\n\n3. Connect to the right link about linkedin and Twitter\n\n4. The contect me seems not actually work\n",
    "createdAt": "2025-04-16T00:38:47.978Z",
    "updatedAt": "2025-04-16T01:00:00.848Z",
    "comments": []
  },
  {
    "id": "1745311887815",
    "title": "2025-4-22 A short review of my first First Flight",
    "content": "(Bug found: 1Medium, 2Low. The link to the contest \"https://codehawks.cyfrin.io/c/2025-04-eggstravaganza\")\nThe total number of bug in this ``Eggstravaganza `` first flight is 10( includes 2 High, 4 Medium, 4 Low. But I only found 1 medium and 2 low), which is really make me upset. But in the other side, it means there are too many things I can learn from this contest.\n\n1. Ownership check is essential in all kinds of code ( includes access control, ownership seperation in different contracts ...etc\n\nalways remember to determine who should or shouldn't access this function. How large the disaster can be when  a melicious person use the wrong/miss ownership vulnerability\n\n2. It leaves a vulnerability when interact with ERC721 using _mint instead of using _safeMint/ using transferFrom instead of using safeTransferFrom.\n\nIn summary, you should always remeber to consider a bad situation that the recipient not set the ERC721 receiver interface correctly. The NFT would loss if the address couldn't handle the NFT.\n",
    "createdAt": "2025-04-22T08:51:27.815Z",
    "updatedAt": "2025-04-22T08:57:57.041Z",
    "comments": []
  },
  {
    "id": "1745554173454",
    "title": "智能合约审计中重要的ERC和EIP标准(Ai 生成）",
    "content": "作为刚入门的智能合约审计员，了解以下ERC（以太坊征求意见）和EIP（以太坊改进提案）标准对你的审计工作至关重要：\n\n\n代币标准\nERC20 - 可替代代币标准\n审计要点：余额计算、授权机制、转账逻辑、整数溢出\n\nERC721 - 非同质化代币(NFT)标准\n审计要点：所有权验证、铸造/销毁逻辑、转账安全\n\nERC777 - ERC20的高级替代品，带有钩子功能\n审计要点：重入攻击风险、钩子函数安全\n\nERC1155 - 多代币标准(同时支持FT和NFT)\n审计要点：批量操作安全、元数据处理\n\n\n安全与升级\nERC1967 - 代理存储插槽标准\n审计要点：代理模式实现、存储冲突\n\nEIP1559 - 以太坊费用市场改革\n审计要点：gas使用优化、交易费用处理\n\nEIP2535 - 钻石标准(多面代理合约)\n审计要点：存储布局、函数选择器冲突\n\nERC7201 - 命名空间存储布局\n审计要点：存储槽冲突、升级安全性\n\n\n数据与身份\nERC165 - 接口检测标准\n审计要点：接口识别实现正确性\n\nERC725 - 身份与密钥管理标准\n审计要点：权限管理、密钥验证\n\n\nDeFi专用\nEIP2612 - 允许通过签名进行ERC20批准\n审计要点：签名验证、重放攻击防护\n\nERC4626 - 代币化资金库标准\n审计要点：储蓄计算、存款/提款逻辑、份额计算\n\n\n其他关键提案\nERC223 - 防止代币丢失的转账标准\n审计要点：接收者验证逻辑\n\nEIP140/EIP214 - STATICCALL操作码\n审计要点：状态修改防护、只读调用\n\nEIP1884 - 调整某些EVM操作码的gas成本\n审计要点：gas使用效率、潜在的DoS风险\n\n\n审计实践建议\n使用自动化工具如Slither、Mythril和Echidna进行初步扫描\n关注存储布局，特别是在可升级合约中\n检查权限控制和角色分配\n审计所有数学计算，寻找整数溢出/下溢\n验证外部调用的安全处理\n对于每个审计项目，建议根据合约的具体功能和使用的标准，制定相应的审计清单。这些标准不仅提供了实现指南，也是发现潜在漏洞的关键参考点。",
    "createdAt": "2025-04-25T04:09:33.454Z",
    "updatedAt": "2025-04-25T04:09:33.454Z",
    "comments": []
  }
]